pyunit_gof/__init__.py
pyunit_gof/chain.py
pyunit_gof/clone.py
pyunit_gof/mediator.py
pyunit_gof/observer.py
pyunit_gof/proxy.py
pyunit_gof/singleton.py
pyunit_gof/state1.py
pyunit_gof/state2.py
pyunit_gof-2020.3.11.dist-info/METADATA
pyunit_gof-2020.3.11.dist-info/WHEEL
pyunit_gof-2020.3.11.dist-info/top_level.txt
pyunit_gof-2020.3.11.dist-info/RECORD
