Metadata-Version: 2.1
Name: pyunit-gof
Version: 2020.3.11
Summary: 设计模式接口
Home-page: https://github.com/PyUnit/pyunit-gof
Author: Jtyoui
Author-email: jtyoui@qq.com
License: MIT Licence
Platform: any
Classifier: Programming Language :: Python :: 3
Classifier: License :: OSI Approved :: MIT License
Classifier: Operating System :: OS Independent
